mixnet/__init__.py
mixnet/callbacks.py
mixnet/gradients.py
mixnet/loss.py
mixnet/trainer.py
mixnet/utils.py
mixnet/version.py
mixnet/models/DeepConvNet.py
mixnet/models/EEGNet.py
mixnet/models/MIN2Net_original.py
mixnet/models/MixNet.py
mixnet/models/SVM.py
mixnet/models/SpectralSpatialCNN.py
mixnet/models/__init__.py
mixnet/models/base.py
mixnet/preprocessing/FBCSP.py
mixnet/preprocessing/SpectralSpatialMapping.py
mixnet/preprocessing/SpectralSpatialSignalGeneration.py
mixnet/preprocessing/__init__.py
mixnet/preprocessing/config.py
mixnet/preprocessing/BCIC2a/__init__.py
mixnet/preprocessing/BCIC2a/fbcsp.py
mixnet/preprocessing/BCIC2a/raw.py
mixnet/preprocessing/BCIC2a/spectral_spatial.py
mixnet/preprocessing/BCIC2a/spectral_spatial_signals.py
mixnet/preprocessing/BCIC2a/time_domain.py
mixnet/preprocessing/BCIC2b/__init__.py
mixnet/preprocessing/BCIC2b/fbcsp.py
mixnet/preprocessing/BCIC2b/raw.py
mixnet/preprocessing/BCIC2b/spectral_spatial.py
mixnet/preprocessing/BCIC2b/spectral_spatial_signals.py
mixnet/preprocessing/BCIC2b/time_domain.py
mixnet/preprocessing/BNCI2015_001/__init__.py
mixnet/preprocessing/BNCI2015_001/fbcsp.py
mixnet/preprocessing/BNCI2015_001/raw.py
mixnet/preprocessing/BNCI2015_001/spectral_spatial.py
mixnet/preprocessing/BNCI2015_001/spectral_spatial_signals.py
mixnet/preprocessing/BNCI2015_001/time_domain.py
mixnet/preprocessing/HighGamma/__init__.py
mixnet/preprocessing/HighGamma/fbcsp.py
mixnet/preprocessing/HighGamma/raw.py
mixnet/preprocessing/HighGamma/spectral_spatial.py
mixnet/preprocessing/HighGamma/spectral_spatial_signals.py
mixnet/preprocessing/HighGamma/time_domain.py
mixnet/preprocessing/OpenBMI/__init__.py
mixnet/preprocessing/OpenBMI/fbcsp.py
mixnet/preprocessing/OpenBMI/raw.py
mixnet/preprocessing/OpenBMI/spectral_spatial.py
mixnet/preprocessing/OpenBMI/spectral_spatial_signals.py
mixnet/preprocessing/OpenBMI/time_domain.py
mixnet/preprocessing/SMR_BCI/__init__.py
mixnet/preprocessing/SMR_BCI/fbcsp.py
mixnet_bci-1.0.0.dist-info/LICENSE
mixnet_bci-1.0.0.dist-info/METADATA
mixnet_bci-1.0.0.dist-info/WHEEL
mixnet_bci-1.0.0.dist-info/top_level.txt
mixnet_bci-1.0.0.dist-info/RECORD
