Metadata-Version: 2.1
Name: mixnet-bci
Version: 1.0.0
Summary: MixNet: Joining Force of Classical and Modern Approaches toward The Comprehensive Pipeline in Motor Imagery EEG Classification
Home-page: https://github.com/Max-Phairot-A/MixNet
Author: Phairot Autthasan
Author-email: phairot.a_s17@vistec.ac.th
License: Apache Software License
Download-URL: https://github.com/Max-Phairot-A/MixNet/releases
Project-URL: Bug Tracker, https://github.com/Max-Phairot-A/MixNet/issues
Project-URL: Documentation, https://github.com/Max-Phairot-A/MixNet
Project-URL: Source Code, https://github.com/Max-Phairot-A/MixNet
Keywords: Brain-computer Interfaces,BCI,Deep learning,DLMotor Imagery,MI,Multi-task Learning,Deep Metric Learning,DML,Autoencoder,AE,Adaptive Gradient Blending,EEG Classifier
Platform: UNKNOWN
Classifier: Programming Language :: Python :: 3
Classifier: License :: OSI Approved :: Apache Software License
Classifier: Operating System :: OS Independent
Requires-Python: >=3.8, <=3.10.4
License-File: LICENSE
Requires-Dist: tensorflow-addons (==0.16.1)
Requires-Dist: scikit-learn (>=1.2.2)
Requires-Dist: wget (>=3.2)
Requires-Dist: ray (>=1.11.0)
Requires-Dist: pandas
